[
    {
        "items": [
            {
                "seating": "12", 
                "phone": false, 
                "manager": "Finance, Andrea Waters", 
                "hasUsageRestrictions": true, 
                "id": 1, 
                "building": 1, 
                "network": false, 
                "usageRestrictions": "Restrictions exist; unknown", 
                "roomNumber": "112", 
                "generalUsage": true, 
                "type": "Conference Room", 
                "display": true
            }, 
            {
                "seating": "200", 
                "phone": false, 
                "manager": "City Manager's Office", 
                "hasUsageRestrictions": true, 
                "id": 2, 
                "building": 1, 
                "network": false, 
                "usageRestrictions": "Restrictions exist; unknown", 
                "roomNumber": "201", 
                "generalUsage": true, 
                "type": "Council Chamber", 
                "display": true
            }, 
            {
                "seating": "12", 
                "phone": false, 
                "manager": "City Council", 
                "hasUsageRestrictions": false, 
                "id": 3, 
                "building": 1, 
                "network": false, 
                "usageRestrictions": "n/a", 
                "roomNumber": "213", 
                "generalUsage": false, 
                "type": "Conference Room", 
                "display": false
            }, 
            {
                "seating": "12", 
                "phone": false, 
                "manager": "City Manager's Office", 
                "hasUsageRestrictions": false, 
                "id": 4, 
                "building": 1, 
                "network": false, 
                "usageRestrictions": "n/a", 
                "roomNumber": "228", 
                "generalUsage": false, 
                "type": "Conference Room", 
                "display": false
            }, 
            {
                "seating": "25", 
                "phone": false, 
                "manager": "Parks, Recreation and Cultural Resources / Facilities & Operations", 
                "hasUsageRestrictions": true, 
                "id": 5, 
                "building": 1, 
                "network": false, 
                "usageRestrictions": "None", 
                "roomNumber": "303", 
                "generalUsage": true, 
                "type": "Conference Room", 
                "display": true
            }, 
            {
                "seating": "30", 
                "phone": false, 
                "manager": "City Manager's Office", 
                "hasUsageRestrictions": true, 
                "id": 6, 
                "building": 1, 
                "network": false, 
                "usageRestrictions": "None", 
                "roomNumber": "305", 
                "generalUsage": true, 
                "type": "Conference Room", 
                "display": true
            }, 
            {
                "seating": "8", 
                "phone": false, 
                "manager": "Public Works, Sherry Davis", 
                "hasUsageRestrictions": true, 
                "id": 7, 
                "building": 1, 
                "network": true, 
                "usageRestrictions": "Restrictions exist; unknown", 
                "roomNumber": "408", 
                "generalUsage": true, 
                "type": "Conference Room", 
                "display": false
            }, 
            {
                "seating": "10", 
                "phone": false, 
                "manager": "Public Works, Sherry Davis", 
                "hasUsageRestrictions": true, 
                "id": 8, 
                "building": 1, 
                "network": false, 
                "usageRestrictions": "None", 
                "roomNumber": "419", 
                "generalUsage": true, 
                "type": "Conference Room", 
                "display": true
            }, 
            {
                "seating": "14", 
                "phone": false, 
                "manager": "Information Technology, April Webb", 
                "hasUsageRestrictions": true, 
                "id": 9, 
                "building": 1, 
                "network": false, 
                "usageRestrictions": "None", 
                "roomNumber": "516", 
                "generalUsage": true, 
                "type": "Conference Room", 
                "display": true
            }, 
            {
                "seating": "10", 
                "phone": false, 
                "manager": "Parks, Recreation and Cultural Resources", 
                "hasUsageRestrictions": false, 
                "id": 10, 
                "building": 1, 
                "network": false, 
                "usageRestrictions": "n/a", 
                "roomNumber": "601", 
                "generalUsage": false, 
                "type": "Conference Room", 
                "display": true
            }, 
            {
                "seating": "10", 
                "phone": false, 
                "manager": "Parks, Recreation and Cultural Resources", 
                "hasUsageRestrictions": false, 
                "id": 11, 
                "building": 1, 
                "network": false, 
                "usageRestrictions": "n/a", 
                "roomNumber": "609", 
                "generalUsage": false, 
                "type": "Conference Room", 
                "display": true
            }, 
            {
                "seating": "0", 
                "phone": false, 
                "manager": "Public Works, Debbie Wyatt", 
                "hasUsageRestrictions": true, 
                "id": 12, 
                "building": 2, 
                "network": false, 
                "usageRestrictions": "None", 
                "roomNumber": "312", 
                "generalUsage": true, 
                "type": "Conference Room", 
                "display": false
            }, 
            {
                "seating": "20", 
                "phone": false, 
                "manager": "Public Utilities", 
                "hasUsageRestrictions": false, 
                "id": 13, 
                "building": 2, 
                "network": false, 
                "usageRestrictions": "n/a", 
                "roomNumber": "601", 
                "generalUsage": false, 
                "type": "Conference Room", 
                "display": false
            }, 
            {
                "seating": "10", 
                "phone": false, 
                "manager": "Public Utilities", 
                "hasUsageRestrictions": false, 
                "id": 14, 
                "building": 2, 
                "network": false, 
                "usageRestrictions": "n/a", 
                "roomNumber": "602", 
                "generalUsage": false, 
                "type": "Conference Room", 
                "display": false
            }, 
            {
                "seating": "40", 
                "phone": false, 
                "manager": "Parks, Recreation and Cultural Resources / Facilities & Operations", 
                "hasUsageRestrictions": true, 
                "id": 15, 
                "building": 2, 
                "network": false, 
                "usageRestrictions": "None", 
                "roomNumber": "701", 
                "generalUsage": true, 
                "type": "Conference Room", 
                "display": false
            }, 
            {
                "seating": "10", 
                "phone": false, 
                "manager": "Information Technology, April Webb", 
                "hasUsageRestrictions": true, 
                "id": 16, 
                "building": 2, 
                "network": false, 
                "usageRestrictions": "None", 
                "roomNumber": "900-A", 
                "generalUsage": true, 
                "type": "Conference Room", 
                "display": true
            },
            {
                "seating": "0", 
                "phone": false, 
                "manager": "City Attorney", 
                "hasUsageRestrictions": true, 
                "id": 17, 
                "building": 2, 
                "network": false, 
                "usageRestrictions": "None", 
                "roomNumber": "1001", 
                "generalUsage": false, 
                "type": "Conference Room", 
                "display": false
            }, 
            {
                "seating": "8", 
                "phone": false, 
                "manager": "Community Development, Judy Blaeske", 
                "hasUsageRestrictions": true, 
                "id": 18, 
                "building": 3, 
                "network": true, 
                "usageRestrictions": "None", 
                "roomNumber": "-1", 
                "generalUsage": true, 
                "type": "Conference Room", 
                "display": false
            }, 
            {
                "seating": "20", 
                "phone": false, 
                "manager": "Human Resources / Organization Development & Training", 
                "hasUsageRestrictions": false, 
                "id": 19, 
                "building": 4, 
                "network": false, 
                "usageRestrictions": "n/a", 
                "roomNumber": "303", 
                "generalUsage": false, 
                "type": "Unknown", 
                "display": true
            }, 
            {
                "seating": "12", 
                "phone": false, 
                "manager": "Risk Management / Internal Audit", 
                "hasUsageRestrictions": false, 
                "id": 20, 
                "building": 4, 
                "network": false, 
                "usageRestrictions": "n/a", 
                "roomNumber": "400", 
                "generalUsage": false, 
                "type": "Board Room", 
                "display": false
            }, 
            {
                "seating": "25", 
                "phone": false, 
                "manager": "Planning & Development, Rotonda McKoy", 
                "hasUsageRestrictions": true, 
                "id": 21, 
                "building": 5, 
                "network": false, 
                "usageRestrictions": "None", 
                "roomNumber": "-1", 
                "generalUsage": true, 
                "type": "Conference Room", 
                "display": true
            }, 
            {
                "seating": "10", 
                "phone": false, 
                "manager": "Solid Waste Services", 
                "hasUsageRestrictions": true, 
                "id": 22, 
                "building": 6, 
                "network": true, 
                "usageRestrictions": "None", 
                "roomNumber": "415", 
                "generalUsage": true, 
                "type": "Conference Room", 
                "display": false
            }, 
            {
                "seating": "18", 
                "phone": false, 
                "manager": "Solid Waste Services, Patricia Bullock-Peacock", 
                "hasUsageRestrictions": true, 
                "id": 23, 
                "building": 6, 
                "network": true, 
                "usageRestrictions": "None", 
                "roomNumber": "421", 
                "generalUsage": true, 
                "type": "Conference Room", 
                "display": false
            }, 
            {
                "seating": "18", 
                "phone": false, 
                "manager": "Solid Waste Services, Patricia Bullock-Peacock", 
                "hasUsageRestrictions": true, 
                "id": 24, 
                "building": 6, 
                "network": true, 
                "usageRestrictions": "None", 
                "roomNumber": "433", 
                "generalUsage": true, 
                "type": "Conference Room", 
                "display": false
            }, 
            {
                "seating": "18", 
                "phone": false, 
                "manager": "Solid Waste Services, Patricia Bullock-Peacock", 
                "hasUsageRestrictions": true, 
                "id": 25, 
                "building": 6, 
                "network": true, 
                "usageRestrictions": "None", 
                "roomNumber": "420", 
                "generalUsage": true, 
                "type": "Conference Room", 
                "display": false
            }, 
            {
                "seating": "18", 
                "phone": false, 
                "manager": "Solid Waste Services, Patricia Bullock-Peacock", 
                "hasUsageRestrictions": true, 
                "id": 26, 
                "building": 6, 
                "network": true, 
                "usageRestrictions": "None", 
                "roomNumber": "434", 
                "generalUsage": true, 
                "type": "Conference Room", 
                "display": false
            }, 
            {
                "seating": "8", 
                "phone": false, 
                "manager": "Solid Waste Services", 
                "hasUsageRestrictions": true, 
                "id": 27, 
                "building": 6, 
                "network": false, 
                "usageRestrictions": "None", 
                "roomNumber": "442", 
                "generalUsage": true, 
                "type": "Conference Room", 
                "display": true
            }, 
            {
                "seating": "250", 
                "phone": false, 
                "manager": "Solid Waste Services", 
                "hasUsageRestrictions": true, 
                "id": 28, 
                "building": 6, 
                "network": true, 
                "usageRestrictions": "Limited to after 9 a.m.", 
                "roomNumber": "448", 
                "generalUsage": true, 
                "type": "Gathering Room", 
                "display": false
            }, 
            {
                "seating": "12", 
                "phone": false, 
                "manager": "Public Utilities", 
                "hasUsageRestrictions": true, 
                "id": 29, 
                "building": 7, 
                "network": false, 
                "usageRestrictions": "None", 
                "roomNumber": "-1", 
                "generalUsage": true, 
                "type": "Conference Room", 
                "display": false
            }, 
            {
                "seating": "100", 
                "phone": false, 
                "manager": "Public Utilities", 
                "hasUsageRestrictions": true, 
                "id": 30, 
                "building": 7, 
                "network": false, 
                "usageRestrictions": "None", 
                "roomNumber": "-1", 
                "generalUsage": true, 
                "type": "Training Room", 
                "display": true
            }, 
            {
                "seating": "40", 
                "phone": false, 
                "manager": "Public Utilities", 
                "hasUsageRestrictions": true, 
                "id": 31, 
                "building": 8, 
                "network": false, 
                "usageRestrictions": "None", 
                "roomNumber": "-1", 
                "generalUsage": true, 
                "type": "Training Room", 
                "display": true
            }, 
            {
                "seating": "40", 
                "phone": false, 
                "manager": "Public Utilities", 
                "hasUsageRestrictions": true, 
                "id": 32, 
                "building": 9, 
                "network": false, 
                "usageRestrictions": "None", 
                "roomNumber": "-1", 
                "generalUsage": true, 
                "type": "Conference Room", 
                "display": true
            }, 
            {
                "seating": "50", 
                "phone": false, 
                "manager": "Public Utilities", 
                "hasUsageRestrictions": true, 
                "id": 33, 
                "building": 10, 
                "network": false, 
                "usageRestrictions": "None", 
                "roomNumber": "111", 
                "generalUsage": true, 
                "type": "Conference Room", 
                "display": true
            }, 
            {
                "seating": "50", 
                "phone": false, 
                "manager": "Public Utilities", 
                "hasUsageRestrictions": true, 
                "id": 34, 
                "building": 10, 
                "network": false, 
                "usageRestrictions": "None", 
                "roomNumber": "112", 
                "generalUsage": true, 
                "type": "Conference Room", 
                "display": true
            }, 
            {
                "seating": "0", 
                "phone": false, 
                "manager": "Parks, Recreation and Cultural Resources", 
                "hasUsageRestrictions": false, 
                "id": 35, 
                "building": 11, 
                "network": false, 
                "usageRestrictions": "n/a", 
                "roomNumber": "-1", 
                "generalUsage": false, 
                "type": "Conference Room", 
                "display": false
            }, 
            {
                "seating": "20", 
                "phone": false, 
                "manager": "Police", 
                "hasUsageRestrictions": false, 
                "id": 36, 
                "building": 12, 
                "network": false, 
                "usageRestrictions": "n/a", 
                "roomNumber": "-1", 
                "generalUsage": false, 
                "type": "Conference Room", 
                "display": true
            }, 
            {
                "seating": "4", 
                "phone": false, 
                "manager": "Public Works / Transit Admin", 
                "hasUsageRestrictions": false, 
                "id": 37, 
                "building": 13, 
                "network": false, 
                "usageRestrictions": "n/a", 
                "roomNumber": "103", 
                "generalUsage": false, 
                "type": "Conference Room", 
                "display": false
            }, 
            {
                "seating": "10", 
                "phone": false, 
                "manager": "Public Works / Transit Admin", 
                "hasUsageRestrictions": false, 
                "id": 38, 
                "building": 13, 
                "network": true, 
                "usageRestrictions": "n/a", 
                "roomNumber": "209", 
                "generalUsage": false, 
                "type": "Conference Room", 
                "display": false
            }, 
            {
                "seating": "10", 
                "phone": false, 
                "manager": "Public Works / Transit Admin", 
                "hasUsageRestrictions": false, 
                "id": 39, 
                "building": 13, 
                "network": true, 
                "usageRestrictions": "n/a", 
                "roomNumber": "218", 
                "generalUsage": false, 
                "type": "Conference Room", 
                "display": false
            }, 
            {
                "seating": "10", 
                "phone": false, 
                "manager": "Public Works / Transit Operations", 
                "hasUsageRestrictions": false, 
                "id": 40, 
                "building": 13, 
                "network": false, 
                "usageRestrictions": "n/a", 
                "roomNumber": "253", 
                "generalUsage": false, 
                "type": "Conference Room", 
                "display": false
            }, 
            {
                "seating": "10", 
                "phone": false, 
                "manager": "Public Works / Transit Admin", 
                "hasUsageRestrictions": false, 
                "id": 41, 
                "building": 13, 
                "network": true, 
                "usageRestrictions": "n/a", 
                "roomNumber": "406", 
                "generalUsage": false, 
                "type": "Conference Room", 
                "display": false
            }, 
            {
                "seating": "20", 
                "phone": false, 
                "manager": "Police", 
                "hasUsageRestrictions": false, 
                "id": 42, 
                "building": 14, 
                "network": true, 
                "usageRestrictions": "n/a", 
                "roomNumber": "-1", 
                "generalUsage": false, 
                "type": "Unknown", 
                "display": false
            }, 
            {
                "seating": "100", 
                "phone": false, 
                "manager": "Police", 
                "hasUsageRestrictions": false, 
                "id": 43, 
                "building": 15, 
                "network": true, 
                "usageRestrictions": "n/a", 
                "roomNumber": "-1", 
                "generalUsage": false, 
                "type": "Unknown", 
                "display": false
            }, 
            {
                "seating": "10", 
                "phone": false, 
                "manager": "Public Utilities", 
                "hasUsageRestrictions": true, 
                "id": 44, 
                "building": 16, 
                "network": false, 
                "usageRestrictions": "None", 
                "roomNumber": "-1", 
                "generalUsage": true, 
                "type": "Conference Room", 
                "display": false
            }
        ], 
        "model": "room"
    }, 
    {
        "items": [
            {
                "address": "222 W. Hargett Street", 
                "id": 1, 
                "name": "Raleigh Municipal Building"
            }, 
            {
                "address": "1 Exchange Plaza", 
                "id": 2, 
                "name": "One Exchange Plaza"
            }, 
            {
                "address": "310 W Martin Street", 
                "id": 3, 
                "name": "Dillon Building"
            }, 
            {
                "address": "127 W Hargett Street", 
                "id": 4, 
                "name": "Professional Building"
            }, 
            {
                "address": "220 Fayetteville Street", 
                "id": 5, 
                "name": "Urban Design Center"
            }, 
            {
                "address": "630 Beacon Lake Drive", 
                "id": 6, 
                "name": "Wilders Grove Solid Waste Facility"
            }, 
            {
                "address": "8500 Battle Bridge Road", 
                "id": 7, 
                "name": "Neuse River Waste Water Treatment Plant"
            }, 
            {
                "address": "2315 Benson Road", 
                "id": 8, 
                "name": "Dempsey E. Benton Water Treatment Plant"
            }, 
            {
                "address": "10301 Falls of Neuse Road", 
                "id": 9, 
                "name": "E.M. Johnson Water Treatment Plant"
            }, 
            {
                "address": "3304 Lake Woodard Dr", 
                "id": 10, 
                "name": "Lake Woodard Annex"
            }, 
            {
                "address": "3050 N New Hope Road", 
                "id": 11, 
                "name": "Marsh Creek"
            }, 
            {
                "address": "4501 Atlantic Avenue", 
                "id": 12, 
                "name": "RPD Detective Campus"
            }, 
            {
                "address": "4104 Poole Rd", 
                "id": 13, 
                "name": "Raleigh Transit Operations Facility"
            }, 
            {
                "address": "6716 Six Forks Road", 
                "id": 14, 
                "name": "Raleigh Police Department Headquarters"
            }, 
            {
                "address": "601 Hutton Street", 
                "id": 15, 
                "name": "Raleigh Police Department SouthWest District"
            }, 
            {
                "address": "5380 Raynor Road | Garner  NC 27529", 
                "id": 16, 
                "name": "South Raleigh Field Operations Center"
            }
        ], 
        "model": "building"
    }
]